Metadata-Version: 2.1
Name: sponggy
Version: 0.0.1
Summary: sponggy - a Python tool for installing Caddy.
Home-page: https://github.com/fikisipi/sponggy
Author: Filip Dimitrovski
Author-email: filip@tune.mk
License: UNKNOWN
Platform: UNKNOWN
Requires-Python: >=3.5
